[{"drilldownGeographic":"Kalimantan Tengah","Persentase_total_vaksin1_pendidik":"36.903774217","DrillDownMap":"MultiPolygon","Latitude (generated)":"-1.571078623","Longitude (generated)":"113.529180602","Divaksin 1":"25,354"},{"drilldownGeographic":"Bali","Persentase_total_vaksin1_pendidik":"35.507445727","DrillDownMap":"MultiPolygon","Latitude (generated)":"-8.473656133","Longitude (generated)":"115.138411959","Divaksin 1":"29,686"},{"drilldownGeographic":"Aceh","Persentase_total_vaksin1_pendidik":"12.062431996","DrillDownMap":"MultiPolygon","Latitude (generated)":"3.692531012","Longitude (generated)":"96.492951043","Divaksin 1":"22,505"},{"drilldownGeographic":"Kalimantan Timur","Persentase_total_vaksin1_pendidik":"46.204656069","DrillDownMap":"MultiPolygon","Latitude (generated)":"0.186838309","Longitude (generated)":"117.264103540","Divaksin 1":"38,543"},{"drilldownGeographic":"Kalimantan Barat","Persentase_total_vaksin1_pendidik":"25.626849253","DrillDownMap":"MultiPolygon","Latitude (generated)":"-0.480872266","Longitude (generated)":"110.114503401","Divaksin 1":"27,023"},{"drilldownGeographic":"Maluku","Persentase_total_vaksin1_pendidik":"11.688570652","DrillDownMap":"MultiPolygon","Latitude (generated)":"-5.599788367","Longitude (generated)":"130.942872444","Divaksin 1":"6,448"},{"drilldownGeographic":"Banten","Persentase_total_vaksin1_pendidik":"41.412298245","DrillDownMap":"MultiPolygon","Latitude (generated)":"-6.488589797","Longitude (generated)":"105.955829356","Divaksin 1":"85,106"},{"drilldownGeographic":"Jawa Barat","Persentase_total_vaksin1_pendidik":"44.767377260","DrillDownMap":"MultiPolygon","Latitude (generated)":"-6.868354221","Longitude (generated)":"107.595970396","Divaksin 1":"366,639"},{"drilldownGeographic":"Bengkulu","Persentase_total_vaksin1_pendidik":"16.559239080","DrillDownMap":"MultiPolygon","Latitude (generated)":"-3.794219220","Longitude (generated)":"102.656170244","Divaksin 1":"8,966"},{"drilldownGeographic":"Sumatera Selatan","Persentase_total_vaksin1_pendidik":"39.210249856","DrillDownMap":"MultiPolygon","Latitude (generated)":"-3.360627312","Longitude (generated)":"103.952945636","Divaksin 1":"72,408"},{"drilldownGeographic":"Papua","Persentase_total_vaksin1_pendidik":"17.438539732","DrillDownMap":"MultiPolygon","Latitude (generated)":"-3.900313928","Longitude (generated)":"137.250124664","Divaksin 1":"8,732"},{"drilldownGeographic":"Papua Barat","Persentase_total_vaksin1_pendidik":"17.606376249","DrillDownMap":"MultiPolygon","Latitude (generated)":"-1.870280589","Longitude (generated)":"132.069359090","Divaksin 1":"4,175"},{"drilldownGeographic":"Sulawesi Selatan","Persentase_total_vaksin1_pendidik":"35.547266571","DrillDownMap":"MultiPolygon","Latitude (generated)":"-5.044463329","Longitude (generated)":"120.069388382","Divaksin 1":"82,625"},{"drilldownGeographic":"Kepulauan Bangka Belitung","Persentase_total_vaksin1_pendidik":"36.201517291","DrillDownMap":"MultiPolygon","Latitude (generated)":"-2.680760569","Longitude (generated)":"107.091964140","Divaksin 1":"11,023"},{"drilldownGeographic":"Jawa Tengah","Persentase_total_vaksin1_pendidik":"43.011000377","DrillDownMap":"MultiPolygon","Latitude (generated)":"-7.180583817","Longitude (generated)":"110.353867302","Divaksin 1":"281,947"},{"drilldownGeographic":"Nusa Tenggara Timur","Persentase_total_vaksin1_pendidik":"27.456470557","DrillDownMap":"MultiPolygon","Latitude (generated)":"-9.093339591","Longitude (generated)":"121.979126766","Divaksin 1":"41,283"},{"drilldownGeographic":"Yogyakarta","Persentase_total_vaksin1_pendidik":"67.522207374","DrillDownMap":"MultiPolygon","Latitude (generated)":"-7.899486582","Longitude (generated)":"110.477696563","Divaksin 1":"68,716"},{"drilldownGeographic":"Kalimantan Utara","Persentase_total_vaksin1_pendidik":"34.950201884","DrillDownMap":"MultiPolygon","Latitude (generated)":"3.198721505","Longitude (generated)":"117.064922922","Divaksin 1":"6,492"},{"drilldownGeographic":"Jawa Timur","Persentase_total_vaksin1_pendidik":"50.881728849","DrillDownMap":"MultiPolygon","Latitude (generated)":"-7.512676706","Longitude (generated)":"113.319458869","Divaksin 1":"423,712"},{"drilldownGeographic":"Gorontalo","Persentase_total_vaksin1_pendidik":"22.953925189","DrillDownMap":"MultiPolygon","Latitude (generated)":"0.663224413","Longitude (generated)":"122.352124889","Divaksin 1":"7,149"},{"drilldownGeographic":"Lampung","Persentase_total_vaksin1_pendidik":"33.205890374","DrillDownMap":"MultiPolygon","Latitude (generated)":"-5.252326515","Longitude (generated)":"104.953683829","Divaksin 1":"60,883"},{"drilldownGeographic":"Jambi","Persentase_total_vaksin1_pendidik":"26.617180322","DrillDownMap":"MultiPolygon","Latitude (generated)":"-1.783912402","Longitude (generated)":"102.651337094","Divaksin 1":"25,495"},{"drilldownGeographic":"Maluku Utara","Persentase_total_vaksin1_pendidik":"6.867926474","DrillDownMap":"MultiPolygon","Latitude (generated)":"-0.140946147","Longitude (generated)":"127.409189807","Divaksin 1":"2,664"},{"drilldownGeographic":"Kepulauan Riau","Persentase_total_vaksin1_pendidik":"46.653284265","DrillDownMap":"MultiPolygon","Latitude (generated)":"1.404795083","Longitude (generated)":"105.177648231","Divaksin 1":"20,917"},{"drilldownGeographic":"Sumatera Utara","Persentase_total_vaksin1_pendidik":"31.454318267","DrillDownMap":"MultiPolygon","Latitude (generated)":"1.478487321","Longitude (generated)":"98.569544068","Divaksin 1":"102,202"},{"drilldownGeographic":"Sulawesi Tengah","Persentase_total_vaksin1_pendidik":"23.371677816","DrillDownMap":"MultiPolygon","Latitude (generated)":"-0.984496975","Longitude (generated)":"121.885075407","Divaksin 1":"20,683"},{"drilldownGeographic":"Sumatera Barat","Persentase_total_vaksin1_pendidik":"26.734263108","DrillDownMap":"MultiPolygon","Latitude (generated)":"-1.622118437","Longitude (generated)":"100.004471233","Divaksin 1":"41,290"},{"drilldownGeographic":"DKI Jakarta","Persentase_total_vaksin1_pendidik":"93.919132150","DrillDownMap":"MultiPolygon","Latitude (generated)":"-5.981626004","Longitude (generated)":"106.720228229","Divaksin 1":"142,851"},{"drilldownGeographic":"Sulawesi Tenggara","Persentase_total_vaksin1_pendidik":"24.512984931","DrillDownMap":"MultiPolygon","Latitude (generated)":"-4.567389221","Longitude (generated)":"122.457457783","Divaksin 1":"19,114"},{"drilldownGeographic":"Sulawesi Barat","Persentase_total_vaksin1_pendidik":"25.454832027","DrillDownMap":"MultiPolygon","Latitude (generated)":"-2.314504610","Longitude (generated)":"119.336384049","Divaksin 1":"11,305"},{"drilldownGeographic":"Nusa Tenggara Barat","Persentase_total_vaksin1_pendidik":"24.502193092","DrillDownMap":"MultiPolygon","Latitude (generated)":"-8.613133142","Longitude (generated)":"117.614487578","Divaksin 1":"39,327"},{"drilldownGeographic":"Riau","Persentase_total_vaksin1_pendidik":"32.090398280","DrillDownMap":"MultiPolygon","Latitude (generated)":"0.765738737","Longitude (generated)":"102.076986034","Divaksin 1":"51,800"},{"drilldownGeographic":"Sulawesi Utara","Persentase_total_vaksin1_pendidik":"33.352574047","DrillDownMap":"MultiPolygon","Latitude (generated)":"2.104979135","Longitude (generated)":"125.071936412","Divaksin 1":"18,490"},{"drilldownGeographic":"Kalimantan Selatan","Persentase_total_vaksin1_pendidik":"42.979835340","DrillDownMap":"MultiPolygon","Latitude (generated)":"-3.045438412","Longitude (generated)":"116.009272885","Divaksin 1":"44,739"}]